cb_events/__init__.py
cb_events/client.py
cb_events/config.py
cb_events/exceptions.py
cb_events/models.py
cb_events/py.typed
cb_events/router.py
cb_events-5.8.2.dist-info/METADATA
cb_events-5.8.2.dist-info/WHEEL
cb_events-5.8.2.dist-info/licenses/LICENSE
cb_events-5.8.2.dist-info/RECORD
